almanack/__init__.py
almanack/batch_processing.py
almanack/book.py
almanack/cli.py
almanack/git.py
almanack/metrics/data.py
almanack/metrics/entropy/calculate_entropy.py
almanack/metrics/entropy/processing_repositories.py
almanack/metrics/garden_lattice/connectedness.py
almanack/metrics/garden_lattice/practicality.py
almanack/metrics/garden_lattice/understanding.py
almanack/metrics/metrics.yml
almanack/metrics/remote.py
almanack/reporting/report.py
almanack-0.1.13.dist-info/METADATA
almanack-0.1.13.dist-info/WHEEL
almanack-0.1.13.dist-info/entry_points.txt
almanack-0.1.13.dist-info/licenses/LICENSE.txt
almanack-0.1.13.dist-info/RECORD
