Metadata-Version: 2.4
Name: almanack
Version: 0.1.13
Summary: An open-source handbook of applied guidance and tools for sustainable software development and maintenance.
License: BSD-3-Clause
License-File: LICENSE.txt
Author: Software Gardening Community
Requires-Python: >=3.10,<3.14
Classifier: License :: OSI Approved :: BSD License
Classifier: Programming Language :: Python :: 3
Classifier: Programming Language :: Python :: 3.10
Classifier: Programming Language :: Python :: 3.11
Classifier: Programming Language :: Python :: 3.12
Classifier: Programming Language :: Python :: 3.13
Requires-Dist: charset-normalizer (>=3.4.0,<4.0.0)
Requires-Dist: defusedxml (>=0.7.1,<0.8.0)
Requires-Dist: fire (>=0.6,<0.8)
Requires-Dist: pandas (>=2.2.2)
Requires-Dist: pyarrow (>=16)
Requires-Dist: pygit2 (>=1.15.1) ; python_full_version <= "3.12.0"
Requires-Dist: pygit2 (>=1.18.2) ; python_full_version > "3.12.0"
Requires-Dist: pyyaml (>=6.0.1,<7.0.0)
Requires-Dist: requests (>=2.32.3,<3.0.0)
Requires-Dist: tabulate (>=0.9.0,<0.10.0)
